mcp_html_uploader/__init__.py
mcp_html_uploader/server.py
mcp_html_uploader-1.2.4.dist-info/licenses/LICENSE
mcp_html_uploader-1.2.4.dist-info/METADATA
mcp_html_uploader-1.2.4.dist-info/WHEEL
mcp_html_uploader-1.2.4.dist-info/entry_points.txt
mcp_html_uploader-1.2.4.dist-info/top_level.txt
mcp_html_uploader-1.2.4.dist-info/RECORD
