Metadata-Version: 2.4
Name: mcp-html-uploader
Version: 1.2.4
Summary: MCP 服务器 - 提供 HTML 文件创建和阿里云 OSS 上传功能
Author-email: Your Name <your.email@example.com>
License: MIT
Project-URL: Homepage, https://github.com/yourusername/mcp-html-uploader
Project-URL: Repository, https://github.com/yourusername/mcp-html-uploader
Keywords: mcp,html,upload,file-server
Classifier: Development Status :: 4 - Beta
Classifier: Intended Audience :: Developers
Classifier: Programming Language :: Python :: 3
Classifier: Programming Language :: Python :: 3.10
Classifier: Programming Language :: Python :: 3.11
Classifier: Programming Language :: Python :: 3.12
Requires-Python: >=3.10
License-File: LICENSE
Requires-Dist: mcp>=0.9.0
Requires-Dist: httpx>=0.27.0
Requires-Dist: oss2>=2.18.0
Dynamic: license-file
